verilog/Verilog Design/Counter/counter.v
module counter(out, clk, rst);

parameter WIDTH = 8;

input clk, rst;
output [WIDTH-1:0] out;

reg [WIDTH-1:0] out;

always@(posedge clk, posedge rst)
begin
	if(rst)
		out <= 0;
	else
		out <= out+1;
end

endmodule

verilog/Verilog Design/Counter/test.v
module test;

    parameter WIDTH = 10;
    
    reg reset = 0;
    
    
    initial begin
        $dumpfile("test.vcd");
        $dumpvars(0,test);
        
        #17 reset = 1;
        #11 reset = 0;
        #29 reset = 1;
        #5  reset = 0;
        #2000 $finish;
    end
    
    reg clk = 0;
    always #1 clk = ~clk;
    
    wire [WIDTH-1:0] value;
    counter #(WIDTH) c1(value, clk, reset);
    
    initial begin
        $monitor("At time %t, value = %h (%0d)", $time, value, value);
    end
    
endmodule

verilog/Verilog Design/Counter/test.vcd
$date
	Thu Mar 21 12:02:14 2013
$end
$version
	Icarus Verilog
$end
$timescale
	1s
$end
$scope module test $end
$var wire 10 ! value [9:0] $end
$var reg 1 " clk $end
$var reg 1 # reset $end
$scope module c1 $end
$var wire 1 " clk $end
$var wire 1 # rst $end
$var reg 10 $ out [9:0] $end
$upscope $end
$upscope $end
$enddefinitions $end
#0
$dumpvars
bx $
0#
0"
bx !
$end
#1
1"
#2
0"
#3
1"
#4
0"
#5
1"
#6
0"
#7
1"
#8
0"
#9
1"
#10
0"
#11
1"
#12
0"
#13
1"
#14
0"
#15
1"
#16
0"
#17
b0 !
b0 $
1"
1#
#18
0"
#19
1"
#20
0"
#21
1"
#22
0"
#23
1"
#24
0"
#25
1"
#26
0"
#27
1"
#28
0"
0#
#29
b1 !
b1 $
1"
#30
0"
#31
b10 !
b10 $
1"
#32
0"
#33
b11 !
b11 $
1"
#34
0"
#35
b100 !
b100 $
1"
#36
0"
#37
b101 !
b101 $
1"
#38
0"
#39
b110 !
b110 $
1"
#40
0"
#41
b111 !
b111 $
1"
#42
0"
#43
b1000 !
b1000 $
1"
#44
0"
#45
b1001 !
b1001 $
1"
#46
0"
#47
b1010 !
b1010 $
1"
#48
0"
#49
b1011 !
b1011 $
1"
#50
0"
#51
b1100 !
b1100 $
1"
#52
0"
#53
b1101 !
b1101 $
1"
#54
0"
#55
b1110 !
b1110 $
1"
#56
0"
#57
b0 !
b0 $
1"
1#
#58
0"
#59
1"
#60
0"
#61
1"
#62
0"
0#
#63
b1 !
b1 $
1"
#64
0"
#65
b10 !
b10 $
1"
#66
0"
#67
b11 !
b11 $
1"
#68
0"
#69
b100 !
b100 $
1"
#70
0"
#71
b101 !
b101 $
1"
#72
0"
#73
b110 !
b110 $
1"
#74
0"
#75
b111 !
b111 $
1"
#76
0"
#77
b1000 !
b1000 $
1"
#78
0"
#79
b1001 !
b1001 $
1"
#80
0"
#81
b1010 !
b1010 $
1"
#82
0"
#83
b1011 !
b1011 $
1"
#84
0"
#85
b1100 !
b1100 $
1"
#86
0"
#87
b1101 !
b1101 $
1"
#88
0"
#89
b1110 !
b1110 $
1"
#90
0"
#91
b1111 !
b1111 $
1"
#92
0"
#93
b10000 !
b10000 $
1"
#94
0"
#95
b10001 !
b10001 $
1"
#96
0"
#97
b10010 !
b10010 $
1"
#98
0"
#99
b10011 !
b10011 $
1"
#100
0"
#101
b10100 !
b10100 $
1"
#102
0"
#103
b10101 !
b10101 $
1"
#104
0"
#105
b10110 !
b10110 $
1"
#106
0"
#107
b10111 !
b10111 $
1"
#108
0"
#109
b11000 !
b11000 $
1"
#110
0"
#111
b11001 !
b11001 $
1"
#112
0"
#113
b11010 !
b11010 $
1"
#114
0"
#115
b11011 !
b11011 $
1"
#116
0"
#117
b11100 !
b11100 $
1"
#118
0"
#119
b11101 !
b11101 $
1"
#120
0"
#121
b11110 !
b11110 $
1"
#122
0"
#123
b11111 !
b11111 $
1"
#124
0"
#125
b100000 !
b100000 $
1"
#126
0"
#127
b100001 !
b100001 $
1"
#128
0"
#129
b100010 !
b100010 $
1"
#130
0"
#131
b100011 !
b100011 $
1"
#132
0"
#133
b100100 !
b100100 $
1"
#134
0"
#135
b100101 !
b100101 $
1"
#136
0"
#137
b100110 !
b100110 $
1"
#138
0"
#139
b100111 !
b100111 $
1"
#140
0"
#141
b101000 !
b101000 $
1"
#142
0"
#143
b101001 !
b101001 $
1"
#144
0"
#145
b101010 !
b101010 $
1"
#146
0"
#147
b101011 !
b101011 $
1"
#148
0"
#149
b101100 !
b101100 $
1"
#150
0"
#151
b101101 !
b101101 $
1"
#152
0"
#153
b101110 !
b101110 $
1"
#154
0"
#155
b101111 !
b101111 $
1"
#156
0"
#157
b110000 !
b110000 $
1"
#158
0"
#159
b110001 !
b110001 $
1"
#160
0"
#161
b110010 !
b110010 $
1"
#162
0"
#163
b110011 !
b110011 $
1"
#164
0"
#165
b110100 !
b110100 $
1"
#166
0"
#167
b110101 !
b110101 $
1"
#168
0"
#169
b110110 !
b110110 $
1"
#170
0"
#171
b110111 !
b110111 $
1"
#172
0"
#173
b111000 !
b111000 $
1"
#174
0"
#175
b111001 !
b111001 $
1"
#176
0"
#177
b111010 !
b111010 $
1"
#178
0"
#179
b111011 !
b111011 $
1"
#180
0"
#181
b111100 !
b111100 $
1"
#182
0"
#183
b111101 !
b111101 $
1"
#184
0"
#185
b111110 !
b111110 $
1"
#186
0"
#187
b111111 !
b111111 $
1"
#188
0"
#189
b1000000 !
b1000000 $
1"
#190
0"
#191
b1000001 !
b1000001 $
1"
#192
0"
#193
b1000010 !
b1000010 $
1"
#194
0"
#195
b1000011 !
b1000011 $
1"
#196
0"
#197
b1000100 !
b1000100 $
1"
#198
0"
#199
b1000101 !
b1000101 $
1"
#200
0"
#201
b1000110 !
b1000110 $
1"
#202
0"
#203
b1000111 !
b1000111 $
1"
#204
0"
#205
b1001000 !
b1001000 $
1"
#206
0"
#207
b1001001 !
b1001001 $
1"
#208
0"
#209
b1001010 !
b1001010 $
1"
#210
0"
#211
b1001011 !
b1001011 $
1"
#212
0"
#213
b1001100 !
b1001100 $
1"
#214
0"
#215
b1001101 !
b1001101 $
1"
#216
0"
#217
b1001110 !
b1001110 $
1"
#218
0"
#219
b1001111 !
b1001111 $
1"
#220
0"
#221
b1010000 !
b1010000 $
1"
#222
0"
#223
b1010001 !
b1010001 $
1"
#224
0"
#225
b1010010 !
b1010010 $
1"
#226
0"
#227
b1010011 !
b1010011 $
1"
#228
0"
#229
b1010100 !
b1010100 $
1"
#230
0"
#231
b1010101 !
b1010101 $
1"
#232
0"
#233
b1010110 !
b1010110 $
1"
#234
0"
#235
b1010111 !
b1010111 $
1"
#236
0"
#237
b1011000 !
b1011000 $
1"
#238
0"
#239
b1011001 !
b1011001 $
1"
#240
0"
#241
b1011010 !
b1011010 $
1"
#242
0"
#243
b1011011 !
b1011011 $
1"
#244
0"
#245
b1011100 !
b1011100 $
1"
#246
0"
#247
b1011101 !
b1011101 $
1"
#248
0"
#249
b1011110 !
b1011110 $
1"
#250
0"
#251
b1011111 !
b1011111 $
1"
#252
0"
#253
b1100000 !
b1100000 $
1"
#254
0"
#255
b1100001 !
b1100001 $
1"
#256
0"
#257
b1100010 !
b1100010 $
1"
#258
0"
#259
b1100011 !
b1100011 $
1"
#260
0"
#261
b1100100 !
b1100100 $
1"
#262
0"
#263
b1100101 !
b1100101 $
1"
#264
0"
#265
b1100110 !
b1100110 $
1"
#266
0"
#267
b1100111 !
b1100111 $
1"
#268
0"
#269
b1101000 !
b1101000 $
1"
#270
0"
#271
b1101001 !
b1101001 $
1"
#272
0"
#273
b1101010 !
b1101010 $
1"
#274
0"
#275
b1101011 !
b1101011 $
1"
#276
0"
#277
b1101100 !
b1101100 $
1"
#278
0"
#279
b1101101 !
b1101101 $
1"
#280
0"
#281
b1101110 !
b1101110 $
1"
#282
0"
#283
b1101111 !
b1101111 $
1"
#284
0"
#285
b1110000 !
b1110000 $
1"
#286
0"
#287
b1110001 !
b1110001 $
1"
#288
0"
#289
b1110010 !
b1110010 $
1"
#290
0"
#291
b1110011 !
b1110011 $
1"
#292
0"
#293
b1110100 !
b1110100 $
1"
#294
0"
#295
b1110101 !
b1110101 $
1"
#296
0"
#297
b1110110 !
b1110110 $
1"
#298
0"
#299
b1110111 !
b1110111 $
1"
#300
0"
#301
b1111000 !
b1111000 $
1"
#302
0"
#303
b1111001 !
b1111001 $
1"
#304
0"
#305
b1111010 !
b1111010 $
1"
#306
0"
#307
b1111011 !
b1111011 $
1"
#308
0"
#309
b1111100 !
b1111100 $
1"
#310
0"
#311
b1111101 !
b1111101 $
1"
#312
0"
#313
b1111110 !
b1111110 $
1"
#314
0"
#315
b1111111 !
b1111111 $
1"
#316
0"
#317
b10000000 !
b10000000 $
1"
#318
0"
#319
b10000001 !
b10000001 $
1"
#320
0"
#321
b10000010 !
b10000010 $
1"
#322
0"
#323
b10000011 !
b10000011 $
1"
#324
0"
#325
b10000100 !
b10000100 $
1"
#326
0"
#327
b10000101 !
b10000101 $
1"
#328
0"
#329
b10000110 !
b10000110 $
1"
#330
0"
#331
b10000111 !
b10000111 $
1"
#332
0"
#333
b10001000 !
b10001000 $
1"
#334
0"
#335
b10001001 !
b10001001 $
1"
#336
0"
#337
b10001010 !
b10001010 $
1"
#338
0"
#339
b10001011 !
b10001011 $
1"
#340
0"
#341
b10001100 !
b10001100 $
1"
#342
0"
#343
b10001101 !
b10001101 $
1"
#344
0"
#345
b10001110 !
b10001110 $
1"
#346
0"
#347
b10001111 !
b10001111 $
1"
#348
0"
#349
b10010000 !
b10010000 $
1"
#350
0"
#351
b10010001 !
b10010001 $
1"
#352
0"
#353
b10010010 !
b10010010 $
1"
#354
0"
#355
b10010011 !
b10010011 $
1"
#356
0"
#357
b10010100 !
b10010100 $
1"
#358
0"
#359
b10010101 !
b10010101 $
1"
#360
0"
#361
b10010110 !
b10010110 $
1"
#362
0"
#363
b10010111 !
b10010111 $
1"
#364
0"
#365
b10011000 !
b10011000 $
1"
#366
0"
#367
b10011001 !
b10011001 $
1"
#368
0"
#369
b10011010 !
b10011010 $
1"
#370
0"
#371
b10011011 !
b10011011 $
1"
#372
0"
#373
b10011100 !
b10011100 $
1"
#374
0"
#375
b10011101 !
b10011101 $
1"
#376
0"
#377
b10011110 !
b10011110 $
1"
#378
0"
#379
b10011111 !
b10011111 $
1"
#380
0"
#381
b10100000 !
b10100000 $
1"
#382
0"
#383
b10100001 !
b10100001 $
1"
#384
0"
#385
b10100010 !
b10100010 $
1"
#386
0"
#387
b10100011 !
b10100011 $
1"
#388
0"
#389
b10100100 !
b10100100 $
1"
#390
0"
#391
b10100101 !
b10100101 $
1"
#392
0"
#393
b10100110 !
b10100110 $
1"
#394
0"
#395
b10100111 !
b10100111 $
1"
#396
0"
#397
b10101000 !
b10101000 $
1"
#398
0"
#399
b10101001 !
b10101001 $
1"
#400
0"
#401
b10101010 !
b10101010 $
1"
#402
0"
#403
b10101011 !
b10101011 $
1"
#404
0"
#405
b10101100 !
b10101100 $
1"
#406
0"
#407
b10101101 !
b10101101 $
1"
#408
0"
#409
b10101110 !
b10101110 $
1"
#410
0"
#411
b10101111 !
b10101111 $
1"
#412
0"
#413
b10110000 !
b10110000 $
1"
#414
0"
#415
b10110001 !
b10110001 $
1"
#416
0"
#417
b10110010 !
b10110010 $
1"
#418
0"
#419
b10110011 !
b10110011 $
1"
#420
0"
#421
b10110100 !
b10110100 $
1"
#422
0"
#423
b10110101 !
b10110101 $
1"
#424
0"
#425
b10110110 !
b10110110 $
1"
#426
0"
#427
b10110111 !
b10110111 $
1"
#428
0"
#429
b10111000 !
b10111000 $
1"
#430
0"
#431
b10111001 !
b10111001 $
1"
#432
0"
#433
b10111010 !
b10111010 $
1"
#434
0"
#435
b10111011 !
b10111011 $
1"
#436
0"
#437
b10111100 !
b10111100 $
1"
#438
0"
#439
b10111101 !
b10111101 $
1"
#440
0"
#441
b10111110 !
b10111110 $
1"
#442
0"
#443
b10111111 !
b10111111 $
1"
#444
0"
#445
b11000000 !
b11000000 $
1"
#446
0"
#447
b11000001 !
b11000001 $
1"
#448
0"
#449
b11000010 !
b11000010 $
1"
#450
0"
#451
b11000011 !
b11000011 $
1"
#452
0"
#453
b11000100 !
b11000100 $
1"
#454
0"
#455
b11000101 !
b11000101 $
1"
#456
0"
#457
b11000110 !
b11000110 $
1"
#458
0"
#459
b11000111 !
b11000111 $
1"
#460
0"
#461
b11001000 !
b11001000 $
1"
#462
0"
#463
b11001001 !
b11001001 $
1"
#464
0"
#465
b11001010 !
b11001010 $
1"
#466
0"
#467
b11001011 !
b11001011 $
1"
#468
0"
#469
b11001100 !
b11001100 $
1"
#470
0"
#471
b11001101 !
b11001101 $
1"
#472
0"
#473
b11001110 !
b11001110 $
1"
#474
0"
#475
b11001111 !
b11001111 $
1"
#476
0"
#477
b11010000 !
b11010000 $
1"
#478
0"
#479
b11010001 !
b11010001 $
1"
#480
0"
#481
b11010010 !
b11010010 $
1"
#482
0"
#483
b11010011 !
b11010011 $
1"
#484
0"
#485
b11010100 !
b11010100 $
1"
#486
0"
#487
b11010101 !
b11010101 $
1"
#488
0"
#489
b11010110 !
b11010110 $
1"
#490
0"
#491
b11010111 !
b11010111 $
1"
#492
0"
#493
b11011000 !
b11011000 $
1"
#494
0"
#495
b11011001 !
b11011001 $
1"
#496
0"
#497
b11011010 !
b11011010 $
1"
#498
0"
#499
b11011011 !
b11011011 $
1"
#500
0"
#501
b11011100 !
b11011100 $
1"
#502
0"
#503
b11011101 !
b11011101 $
1"
#504
0"
#505
b11011110 !
b11011110 $
1"
#506
0"
#507
b11011111 !
b11011111 $
1"
#508
0"
#509
b11100000 !
b11100000 $
1"
#510
0"
#511
b11100001 !
b11100001 $
1"
#512
0"
#513
b11100010 !
b11100010 $
1"
#514
0"
#515
b11100011 !
b11100011 $
1"
#516
0"
#517
b11100100 !
b11100100 $
1"
#518
0"
#519
b11100101 !
b11100101 $
1"
#520
0"
#521
b11100110 !
b11100110 $
1"
#522
0"
#523
b11100111 !
b11100111 $
1"
#524
0"
#525
b11101000 !
b11101000 $
1"
#526
0"
#527
b11101001 !
b11101001 $
1"
#528
0"
#529
b11101010 !
b11101010 $
1"
#530
0"
#531
b11101011 !
b11101011 $
1"
#532
0"
#533
b11101100 !
b11101100 $
1"
#534
0"
#535
b11101101 !
b11101101 $
1"
#536
0"
#537
b11101110 !
b11101110 $
1"
#538
0"
#539
b11101111 !
b11101111 $
1"
#540
0"
#541
b11110000 !
b11110000 $
1"
#542
0"
#543
b11110001 !
b11110001 $
1"
#544
0"
#545
b11110010 !
b11110010 $
1"
#546
0"
#547
b11110011 !
b11110011 $
1"
#548
0"
#549
b11110100 !
b11110100 $
1"
#550
0"
#551
b11110101 !
b11110101 $
1"
#552
0"
#553
b11110110 !
b11110110 $
1"
#554
0"
#555
b11110111 !
b11110111 $
1"
#556
0"
#557
b11111000 !
b11111000 $
1"
#558
0"
#559
b11111001 !
b11111001 $
1"
#560
0"
#561
b11111010 !
b11111010 $
1"
#562
0"
#563
b11111011 !
b11111011 $
1"
#564
0"
#565
b11111100 !
b11111100 $
1"
#566
0"
#567
b11111101 !
b11111101 $
1"
#568
0"
#569
b11111110 !
b11111110 $
1"
#570
0"
#571
b11111111 !
b11111111 $
1"
#572
0"
#573
b100000000 !
b100000000 $
1"
#574
0"
#575
b100000001 !
b100000001 $
1"
#576
0"
#577
b100000010 !
b100000010 $
1"
#578
0"
#579
b100000011 !
b100000011 $
1"
#580
0"
#581
b100000100 !
b100000100 $
1"
#582
0"
#583
b100000101 !
b100000101 $
1"
#584
0"
#585
b100000110 !
b100000110 $
1"
#586
0"
#587
b100000111 !
b100000111 $
1"
#588
0"
#589
b100001000 !
b100001000 $
1"
#590
0"
#591
b100001001 !
b100001001 $
1"
#592
0"
#593
b100001010 !
b100001010 $
1"
#594
0"
#595
b100001011 !
b100001011 $
1"
#596
0"
#597
b100001100 !
b100001100 $
1"
#598
0"
#599
b100001101 !
b100001101 $
1"
#600
0"
#601
b100001110 !
b100001110 $
1"
#602
0"
#603
b100001111 !
b100001111 $
1"
#604
0"
#605
b100010000 !
b100010000 $
1"
#606
0"
#607
b100010001 !
b100010001 $
1"
#608
0"
#609
b100010010 !
b100010010 $
1"
#610
0"
#611
b100010011 !
b100010011 $
1"
#612
0"
#613
b100010100 !
b100010100 $
1"
#614
0"
#615
b100010101 !
b100010101 $
1"
#616
0"
#617
b100010110 !
b100010110 $
1"
#618
0"
#619
b100010111 !
b100010111 $
1"
#620
0"
#621
b100011000 !
b100011000 $
1"
#622
0"
#623
b100011001 !
b100011001 $
1"
#624
0"
#625
b100011010 !
b100011010 $
1"
#626
0"
#627
b100011011 !
b100011011 $
1"
#628
0"
#629
b100011100 !
b100011100 $
1"
#630
0"
#631
b100011101 !
b100011101 $
1"
#632
0"
#633
b100011110 !
b100011110 $
1"
#634
0"
#635
b100011111 !
b100011111 $
1"
#636
0"
#637
b100100000 !
b100100000 $
1"
#638
0"
#639
b100100001 !
b100100001 $
1"
#640
0"
#641
b100100010 !
b100100010 $
1"
#642
0"
#643
b100100011 !
b100100011 $
1"
#644
0"
#645
b100100100 !
b100100100 $
1"
#646
0"
#647
b100100101 !
b100100101 $
1"
#648
0"
#649
b100100110 !
b100100110 $
1"
#650
0"
#651
b100100111 !
b100100111 $
1"
#652
0"
#653
b100101000 !
b100101000 $
1"
#654
0"
#655
b100101001 !
b100101001 $
1"
#656
0"
#657
b100101010 !
b100101010 $
1"
#658
0"
#659
b100101011 !
b100101011 $
1"
#660
0"
#661
b100101100 !
b100101100 $
1"
#662
0"
#663
b100101101 !
b100101101 $
1"
#664
0"
#665
b100101110 !
b100101110 $
1"
#666
0"
#667
b100101111 !
b100101111 $
1"
#668
0"
#669
b100110000 !
b100110000 $
1"
#670
0"
#671
b100110001 !
b100110001 $
1"
#672
0"
#673
b100110010 !
b100110010 $
1"
#674
0"
#675
b100110011 !
b100110011 $
1"
#676
0"
#677
b100110100 !
b100110100 $
1"
#678
0"
#679
b100110101 !
b100110101 $
1"
#680
0"
#681
b100110110 !
b100110110 $
1"
#682
0"
#683
b100110111 !
b100110111 $
1"
#684
0"
#685
b100111000 !
b100111000 $
1"
#686
0"
#687
b100111001 !
b100111001 $
1"
#688
0"
#689
b100111010 !
b100111010 $
1"
#690
0"
#691
b100111011 !
b100111011 $
1"
#692
0"
#693
b100111100 !
b100111100 $
1"
#694
0"
#695
b100111101 !
b100111101 $
1"
#696
0"
#697
b100111110 !
b100111110 $
1"
#698
0"
#699
b100111111 !
b100111111 $
1"
#700
0"
#701
b101000000 !
b101000000 $
1"
#702
0"
#703
b101000001 !
b101000001 $
1"
#704
0"
#705
b101000010 !
b101000010 $
1"
#706
0"
#707
b101000011 !
b101000011 $
1"
#708
0"
#709
b101000100 !
b101000100 $
1"
#710
0"
#711
b101000101 !
b101000101 $
1"
#712
0"
#713
b101000110 !
b101000110 $
1"
#714
0"
#715
b101000111 !
b101000111 $
1"
#716
0"
#717
b101001000 !
b101001000 $
1"
#718
0"
#719
b101001001 !
b101001001 $
1"
#720
0"
#721
b101001010 !
b101001010 $
1"
#722
0"
#723
b101001011 !
b101001011 $
1"
#724
0"
#725
b101001100 !
b101001100 $
1"
#726
0"
#727
b101001101 !
b101001101 $
1"
#728
0"
#729
b101001110 !
b101001110 $
1"
#730
0"
#731
b101001111 !
b101001111 $
1"
#732
0"
#733
b101010000 !
b101010000 $
1"
#734
0"
#735
b101010001 !
b101010001 $
1"
#736
0"
#737
b101010010 !
b101010010 $
1"
#738
0"
#739
b101010011 !
b101010011 $
1"
#740
0"
#741
b101010100 !
b101010100 $
1"
#742
0"
#743
b101010101 !
b101010101 $
1"
#744
0"
#745
b101010110 !
b101010110 $
1"
#746
0"
#747
b101010111 !
b101010111 $
1"
#748
0"
#749
b101011000 !
b101011000 $
1"
#750
0"
#751
b101011001 !
b101011001 $
1"
#752
0"
#753
b101011010 !
b101011010 $
1"
#754
0"
#755
b101011011 !
b101011011 $
1"
#756
0"
#757
b101011100 !
b101011100 $
1"
#758
0"
#759
b101011101 !
b101011101 $
1"
#760
0"
#761
b101011110 !
b101011110 $
1"
#762
0"
#763
b101011111 !
b101011111 $
1"
#764
0"
#765
b101100000 !
b101100000 $
1"
#766
0"
#767
b101100001 !
b101100001 $
1"
#768
0"
#769
b101100010 !
b101100010 $
1"
#770
0"
#771
b101100011 !
b101100011 $
1"
#772
0"
#773
b101100100 !
b101100100 $
1"
#774
0"
#775
b101100101 !
b101100101 $
1"
#776
0"
#777
b101100110 !
b101100110 $
1"
#778
0"
#779
b101100111 !
b101100111 $
1"
#780
0"
#781
b101101000 !
b101101000 $
1"
#782
0"
#783
b101101001 !
b101101001 $
1"
#784
0"
#785
b101101010 !
b101101010 $
1"
#786
0"
#787
b101101011 !
b101101011 $
1"
#788
0"
#789
b101101100 !
b101101100 $
1"
#790
0"
#791
b101101101 !
b101101101 $
1"
#792
0"
#793
b101101110 !
b101101110 $
1"
#794
0"
#795
b101101111 !
b101101111 $
1"
#796
0"
#797
b101110000 !
b101110000 $
1"
#798
0"
#799
b101110001 !
b101110001 $
1"
#800
0"
#801
b101110010 !
b101110010 $
1"
#802
0"
#803
b101110011 !
b101110011 $
1"
#804
0"
#805
b101110100 !
b101110100 $
1"
#806
0"
#807
b101110101 !
b101110101 $
1"
#808
0"
#809
b101110110 !
b101110110 $
1"
#810
0"
#811
b101110111 !
b101110111 $
1"
#812
0"
#813
b101111000 !
b101111000 $
1"
#814
0"
#815
b101111001 !
b101111001 $
1"
#816
0"
#817
b101111010 !
b101111010 $
1"
#818
0"
#819
b101111011 !
b101111011 $
1"
#820
0"
#821
b101111100 !
b101111100 $
1"
#822
0"
#823
b101111101 !
b101111101 $
1"
#824
0"
#825
b101111110 !
b101111110 $
1"
#826
0"
#827
b101111111 !
b101111111 $
1"
#828
0"
#829
b110000000 !
b110000000 $
1"
#830
0"
#831
b110000001 !
b110000001 $
1"
#832
0"
#833
b110000010 !
b110000010 $
1"
#834
0"
#835
b110000011 !
b110000011 $
1"
#836
0"
#837
b110000100 !
b110000100 $
1"
#838
0"
#839
b110000101 !
b110000101 $
1"
#840
0"
#841
b110000110 !
b110000110 $
1"
#842
0"
#843
b110000111 !
b110000111 $
1"
#844
0"
#845
b110001000 !
b110001000 $
1"
#846
0"
#847
b110001001 !
b110001001 $
1"
#848
0"
#849
b110001010 !
b110001010 $
1"
#850
0"
#851
b110001011 !
b110001011 $
1"
#852
0"
#853
b110001100 !
b110001100 $
1"
#854
0"
#855
b110001101 !
b110001101 $
1"
#856
0"
#857
b110001110 !
b110001110 $
1"
#858
0"
#859
b110001111 !
b110001111 $
1"
#860
0"
#861
b110010000 !
b110010000 $
1"
#862
0"
#863
b110010001 !
b110010001 $
1"
#864
0"
#865
b110010010 !
b110010010 $
1"
#866
0"
#867
b110010011 !
b110010011 $
1"
#868
0"
#869
b110010100 !
b110010100 $
1"
#870
0"
#871
b110010101 !
b110010101 $
1"
#872
0"
#873
b110010110 !
b110010110 $
1"
#874
0"
#875
b110010111 !
b110010111 $
1"
#876
0"
#877
b110011000 !
b110011000 $
1"
#878
0"
#879
b110011001 !
b110011001 $
1"
#880
0"
#881
b110011010 !
b110011010 $
1"
#882
0"
#883
b110011011 !
b110011011 $
1"
#884
0"
#885
b110011100 !
b110011100 $
1"
#886
0"
#887
b110011101 !
b110011101 $
1"
#888
0"
#889
b110011110 !
b110011110 $
1"
#890
0"
#891
b110011111 !
b110011111 $
1"
#892
0"
#893
b110100000 !
b110100000 $
1"
#894
0"
#895
b110100001 !
b110100001 $
1"
#896
0"
#897
b110100010 !
b110100010 $
1"
#898
0"
#899
b110100011 !
b110100011 $
1"
#900
0"
#901
b110100100 !
b110100100 $
1"
#902
0"
#903
b110100101 !
b110100101 $
1"
#904
0"
#905
b110100110 !
b110100110 $
1"
#906
0"
#907
b110100111 !
b110100111 $
1"
#908
0"
#909
b110101000 !
b110101000 $
1"
#910
0"
#911
b110101001 !
b110101001 $
1"
#912
0"
#913
b110101010 !
b110101010 $
1"
#914
0"
#915
b110101011 !
b110101011 $
1"
#916
0"
#917
b110101100 !
b110101100 $
1"
#918
0"
#919
b110101101 !
b110101101 $
1"
#920
0"
#921
b110101110 !
b110101110 $
1"
#922
0"
#923
b110101111 !
b110101111 $
1"
#924
0"
#925
b110110000 !
b110110000 $
1"
#926
0"
#927
b110110001 !
b110110001 $
1"
#928
0"
#929
b110110010 !
b110110010 $
1"
#930
0"
#931
b110110011 !
b110110011 $
1"
#932
0"
#933
b110110100 !
b110110100 $
1"
#934
0"
#935
b110110101 !
b110110101 $
1"
#936
0"
#937
b110110110 !
b110110110 $
1"
#938
0"
#939
b110110111 !
b110110111 $
1"
#940
0"
#941
b110111000 !
b110111000 $
1"
#942
0"
#943
b110111001 !
b110111001 $
1"
#944
0"
#945
b110111010 !
b110111010 $
1"
#946
0"
#947
b110111011 !
b110111011 $
1"
#948
0"
#949
b110111100 !
b110111100 $
1"
#950
0"
#951
b110111101 !
b110111101 $
1"
#952
0"
#953
b110111110 !
b110111110 $
1"
#954
0"
#955
b110111111 !
b110111111 $
1"
#956
0"
#957
b111000000 !
b111000000 $
1"
#958
0"
#959
b111000001 !
b111000001 $
1"
#960
0"
#961
b111000010 !
b111000010 $
1"
#962
0"
#963
b111000011 !
b111000011 $
1"
#964
0"
#965
b111000100 !
b111000100 $
1"
#966
0"
#967
b111000101 !
b111000101 $
1"
#968
0"
#969
b111000110 !
b111000110 $
1"
#970
0"
#971
b111000111 !
b111000111 $
1"
#972
0"
#973
b111001000 !
b111001000 $
1"
#974
0"
#975
b111001001 !
b111001001 $
1"
#976
0"
#977
b111001010 !
b111001010 $
1"
#978
0"
#979
b111001011 !
b111001011 $
1"
#980
0"
#981
b111001100 !
b111001100 $
1"
#982
0"
#983
b111001101 !
b111001101 $
1"
#984
0"
#985
b111001110 !
b111001110 $
1"
#986
0"
#987
b111001111 !
b111001111 $
1"
#988
0"
#989
b111010000 !
b111010000 $
1"
#990
0"
#991
b111010001 !
b111010001 $
1"
#992
0"
#993
b111010010 !
b111010010 $
1"
#994
0"
#995
b111010011 !
b111010011 $
1"
#996
0"
#997
b111010100 !
b111010100 $
1"
#998
0"
#999
b111010101 !
b111010101 $
1"
#1000
0"
#1001
b111010110 !
b111010110 $
1"
#1002
0"
#1003
b111010111 !
b111010111 $
1"
#1004
0"
#1005
b111011000 !
b111011000 $
1"
#1006
0"
#1007
b111011001 !
b111011001 $
1"
#1008
0"
#1009
b111011010 !
b111011010 $
1"
#1010
0"
#1011
b111011011 !
b111011011 $
1"
#1012
0"
#1013
b111011100 !
b111011100 $
1"
#1014
0"
#1015
b111011101 !
b111011101 $
1"
#1016
0"
#1017
b111011110 !
b111011110 $
1"
#1018
0"
#1019
b111011111 !
b111011111 $
1"
#1020
0"
#1021
b111100000 !
b111100000 $
1"
#1022
0"
#1023
b111100001 !
b111100001 $
1"
#1024
0"
#1025
b111100010 !
b111100010 $
1"
#1026
0"
#1027
b111100011 !
b111100011 $
1"
#1028
0"
#1029
b111100100 !
b111100100 $
1"
#1030
0"
#1031
b111100101 !
b111100101 $
1"
#1032
0"
#1033
b111100110 !
b111100110 $
1"
#1034
0"
#1035
b111100111 !
b111100111 $
1"
#1036
0"
#1037
b111101000 !
b111101000 $
1"
#1038
0"
#1039
b111101001 !
b111101001 $
1"
#1040
0"
#1041
b111101010 !
b111101010 $
1"
#1042
0"
#1043
b111101011 !
b111101011 $
1"
#1044
0"
#1045
b111101100 !
b111101100 $
1"
#1046
0"
#1047
b111101101 !
b111101101 $
1"
#1048
0"
#1049
b111101110 !
b111101110 $
1"
#1050
0"
#1051
b111101111 !
b111101111 $
1"
#1052
0"
#1053
b111110000 !
b111110000 $
1"
#1054
0"
#1055
b111110001 !
b111110001 $
1"
#1056
0"
#1057
b111110010 !
b111110010 $
1"
#1058
0"
#1059
b111110011 !
b111110011 $
1"
#1060
0"
#1061
b111110100 !
b111110100 $
1"
#1062
0"
#1063
b111110101 !
b111110101 $
1"
#1064
0"
#1065
b111110110 !
b111110110 $
1"
#1066
0"
#1067
b111110111 !
b111110111 $
1"
#1068
0"
#1069
b111111000 !
b111111000 $
1"
#1070
0"
#1071
b111111001 !
b111111001 $
1"
#1072
0"
#1073
b111111010 !
b111111010 $
1"
#1074
0"
#1075
b111111011 !
b111111011 $
1"
#1076
0"
#1077
b111111100 !
b111111100 $
1"
#1078
0"
#1079
b111111101 !
b111111101 $
1"
#1080
0"
#1081
b111111110 !
b111111110 $
1"
#1082
0"
#1083
b111111111 !
b111111111 $
1"
#1084
0"
#1085
b1000000000 !
b1000000000 $
1"
#1086
0"
#1087
b1000000001 !
b1000000001 $
1"
#1088
0"
#1089
b1000000010 !
b1000000010 $
1"
#1090
0"
#1091
b1000000011 !
b1000000011 $
1"
#1092
0"
#1093
b1000000100 !
b1000000100 $
1"
#1094
0"
#1095
b1000000101 !
b1000000101 $
1"
#1096
0"
#1097
b1000000110 !
b1000000110 $
1"
#1098
0"
#1099
b1000000111 !
b1000000111 $
1"
#1100
0"
#1101
b1000001000 !
b1000001000 $
1"
#1102
0"
#1103
b1000001001 !
b1000001001 $
1"
#1104
0"
#1105
b1000001010 !
b1000001010 $
1"
#1106
0"
#1107
b1000001011 !
b1000001011 $
1"
#1108
0"
#1109
b1000001100 !
b1000001100 $
1"
#1110
0"
#1111
b1000001101 !
b1000001101 $
1"
#1112
0"
#1113
b1000001110 !
b1000001110 $
1"
#1114
0"
#1115
b1000001111 !
b1000001111 $
1"
#1116
0"
#1117
b1000010000 !
b1000010000 $
1"
#1118
0"
#1119
b1000010001 !
b1000010001 $
1"
#1120
0"
#1121
b1000010010 !
b1000010010 $
1"
#1122
0"
