verilog/Verilog Recap/FF/DFF.v
module DFF(q, d, clk, reset);
  input d, clk, reset;
  output q;
  reg q;

  always @ (negedge clk or posedge reset)
  if (reset) begin
    q <= 1'b0;
  end else begin
    q <= d;
  end

endmodule

verilog/Verilog Recap/Verilog Recap/FF/TFF.v
`include "../FF/DFF.v"

module TFF(q, clk, reset);
  input clk, reset;
  output q;

  DFF d1(q, d, clk, reset);
  not n1(d, q);

endmodule

verilog/Verilog Recap/ALU/ripple_carry_counter.v
`include "../FF/TFF.v"
module ripple_carry_counter(q, clk, reset);

  output [3:0] q;
  input clk, reset;

  TFF t0(q[0], clk, reset);
  TFF t1(q[1], q[0], reset);
  TFF t2(q[2], q[1], reset);
  TFF t3(q[3], q[2], reset);

endmodule

verilog/Verilog Recap/Tests/Ripple_Carry_Counter_test.v
`include "../ALU/ripple_carry_counter.v"

module test;
  reg clk;
  reg reset;
  wire[3:0] q;

  ripple_carry_counter r1(q, clk, reset);

  initial
    clk = 1'b0;
  always
    #5 clk = ~clk;

  initial begin
    $dumpfile("test.vcd");
    $dumpvars(0,test);
    reset = 1'b1;
    #15 reset = 1'b0;
    #180 reset = 1'b1;
    #10 reset = 1'b0;
    #20 $finish;
  end

  initial
    $monitor($time, " Output q = %d", q);

endmodule

verilog/Verilog Recap/Verilog Recap/Tests/test.vcd
$date
	Thu Aug 25 18:56:23 2016
$end
$version
	Icarus Verilog
$end
$timescale
	1s
$end
$scope module test $end
$var wire 4 ! q [3:0] $end
$var reg 1 " clk $end
$var reg 1 # reset $end
$scope module r1 $end
$var wire 1 " clk $end
$var wire 1 # reset $end
$var wire 4 $ q [3:0] $end
$scope module t0 $end
$var wire 1 " clk $end
$var wire 1 % d $end
$var wire 1 # reset $end
$var wire 1 & q $end
$scope module d1 $end
$var wire 1 " clk $end
$var wire 1 % d $end
$var wire 1 # reset $end
$var reg 1 & q $end
$upscope $end
$upscope $end
$scope module t1 $end
$var wire 1 ' clk $end
$var wire 1 ( d $end
$var wire 1 # reset $end
$var wire 1 ) q $end
$scope module d1 $end
$var wire 1 ' clk $end
$var wire 1 ( d $end
$var wire 1 # reset $end
$var reg 1 ) q $end
$upscope $end
$upscope $end
$scope module t2 $end
$var wire 1 * clk $end
$var wire 1 + d $end
$var wire 1 # reset $end
$var wire 1 , q $end
$scope module d1 $end
$var wire 1 * clk $end
$var wire 1 + d $end
$var wire 1 # reset $end
$var reg 1 , q $end
$upscope $end
$upscope $end
$scope module t3 $end
$var wire 1 - clk $end
$var wire 1 . d $end
$var wire 1 # reset $end
$var wire 1 / q $end
$scope module d1 $end
$var wire 1 - clk $end
$var wire 1 . d $end
$var wire 1 # reset $end
$var reg 1 / q $end
$upscope $end
$upscope $end
$upscope $end
$upscope $end
$enddefinitions $end
#0
$dumpvars
0/
1.
0-
0,
1+
0*
0)
1(
0'
0&
1%
b0 $
1#
0"
b0 !
$end
#5
1"
#10
0"
#15
1"
0#
#20
0%
1'
b1 !
b1 $
1&
0"
#25
1"
#30
0(
1*
1)
1%
0'
b10 !
b10 $
0&
0"
#35
1"
#40
0%
1'
b11 !
b11 $
1&
0"
#45
1"
#50
0+
1-
1,
1(
0*
0)
1%
0'
b100 !
b100 $
0&
0"
#55
1"
#60
0%
1'
b101 !
b101 $
1&
0"
#65
1"
#70
0(
1*
1)
1%
0'
b110 !
b110 $
0&
0"
#75
1"
#80
0%
1'
b111 !
b111 $
1&
0"
#85
1"
#90
0.
1/
1+
0-
0,
1(
0*
0)
1%
0'
b1000 !
b1000 $
0&
0"
#95
1"
#100
0%
1'
b1001 !
b1001 $
1&
0"
#105
1"
#110
0(
1*
1)
1%
0'
b1010 !
b1010 $
0&
0"
#115
1"
#120
0%
1'
b1011 !
b1011 $
1&
0"
#125
1"
#130
0+
1-
1,
1(
0*
0)
1%
0'
b1100 !
b1100 $
0&
0"
#135
1"
#140
0%
1'
b1101 !
b1101 $
1&
0"
#145
1"
#150
0(
1*
1)
1%
0'
b1110 !
b1110 $
0&
0"
#155
1"
#160
0%
1'
b1111 !
b1111 $
1&
0"
#165
1"
#170
1.
0/
1+
0-
0,
1(
0*
0)
1%
0'
b0 !
b0 $
0&
0"
#175
1"
#180
0%
1'
b1 !
b1 $
1&
0"
#185
1"
#190
0(
1*
1)
1%
0'
b10 !
b10 $
0&
0"
#195
1(
0*
b0 !
b0 $
0)
1"
1#
#200
0"
#205
1"
0#
#210
0%
1'
b1 !
b1 $
1&
0"
#215
1"
#220
0(
1*
1)
1%
0'
b10 !
b10 $
0&
0"
